Metadata-Version: 2.1
Name: mlflow-emissions-sdk
Version: 0.14
Summary: tracks carbon emissions and logs it to mlfow
License: MIT
License-File: LICENSE
